{
  "students": {
    "1868213058": {
      "class": "ι",
      "name": "Абакановский Влад",
      "lunch": null,
      "school_visit": null
    },
    "1430032907": {
      "class": "ι",
      "name": "Барон Владислав",
      "lunch": true,
      "school_visit": null
    },
    "858573431": {
      "class": "ι",
      "name": "Басков Никита",
      "lunch": true,
      "school_visit": null,
      "reason": null
    },
    "1165447922": {
      "class": "ι",
      "name": "Бухтоярова Анастасия",
      "lunch": true,
      "school_visit": null
    },
    "1165152297": {
      "class": "ι",
      "name": "Зарипов Ылья",
      "lunch": true,
      "school_visit": null,
      "reason": null
    },
    "1344741369": {
      "class": "ι",
      "name": "Иванцова Аня",
      "lunch": null,
      "school_visit": null
    },
    "700026795": {
      "class": "ι",
      "name": "Кеммерер Сергей",
      "lunch": true,
      "school_visit": null
    },
    "400435224": {
      "class": "ι",
      "name": "Кишкин Алексей",
      "lunch": true,
      "school_visit": null
    },
    "1061139622": {
      "class": "ι",
      "name": "Марьясов Владимир",
      "lunch": null,
      "school_visit": null,
      "reason": "уехал в лагерь"
    },
    "1883271571": {
      "class": "ι",
      "name": "Муковозчик Артём",
      "lunch": null,
      "school_visit": null
    },
    "519905246": {
      "class": "ι",
      "name": "Мухомедьянова Тома",
      "lunch": null,
      "school_visit": null,
      "reason": "Уезжаю на конференцию"
    },
    "603377678": {
      "class": "ι",
      "name": "Попов Вадим",
      "lunch": null,
      "school_visit": null,
      "reason": "Приболел, кашель сопли, думаю ко вторнику уже долечусь"
    },
    "1069934389": {
      "class": "ι",
      "name": "Постоева Анастасия",
      "lunch": false,
      "school_visit": false
    },
    "2078652234": {
      "class": "ι",
      "name": "Ровняго Дмитрий",
      "lunch": true,
      "school_visit": null,
      "reason": "Болею"
    },
    "1089524173": {
      "class": "ι",
      "name": "Рудаков Максим",
      "lunch": null,
      "school_visit": null,
      "reason": null
    },
    "979923466": {
      "class": "ι",
      "name": "Совкова София",
      "lunch": true,
      "school_visit": null,
      "reason": "буду на 13 элементе"
    },
    "408045956": {
      "class": "ι",
      "name": "Соловьев Игорь",
      "lunch": null,
      "school_visit": null,
      "reason": "Болезнь"
    },
    "1831580928": {
      "class": "ι",
      "name": "Шкредов Сергей",
      "lunch": true,
      "school_visit": null
    },
    "1998062038": {
      "class": "ι",
      "name": "Юргельян Нина",
      "lunch": null,
      "school_visit": null
    },
    "1987908012": {
      "class": "ι",
      "name": "Яковлев Демьян",
      "lunch": null,
      "school_visit": null
    }
  },
  "deleted": {}
}